{
    "103373454": {
        "rank": 4,
        "user_id": "3517496862",
        "username": "3517496862",
        "alias_name": "3517496862",
        "kuro_name": "3517496862",
        "waves_id": "103373454",
        "total_score": 384.45,
        "char_score_details": [
            {
                "char_id": 1202,
                "phantom_score": 0.45
            },
            {
                "char_id": 1103,
                "phantom_score": 34.32
            },
            {
                "char_id": 1601,
                "phantom_score": 1.88
            },
            {
                "char_id": 1204,
                "phantom_score": 2.4
            },
            {
                "char_id": 1404,
                "phantom_score": 167.01
            },
            {
                "char_id": 1102,
                "phantom_score": 3.42
            },
            {
                "char_id": 1602,
                "phantom_score": 205.04
            },
            {
                "char_id": 1304,
                "phantom_score": 168.2
            },
            {
                "char_id": 1205,
                "phantom_score": 154.14
            },
            {
                "char_id": 1503,
                "phantom_score": 111.79
            },
            {
                "char_id": 1105,
                "phantom_score": 4.46
            },
            {
                "char_id": 1505,
                "phantom_score": 141.31
            },
            {
                "char_id": 1603,
                "phantom_score": 179.41
            },
            {
                "char_id": 1302,
                "phantom_score": 3.03
            },
            {
                "char_id": 1607,
                "phantom_score": 6.37
            },
            {
                "char_id": 1407,
                "phantom_score": 108.14
            },
            {
                "char_id": 1409,
                "phantom_score": 170.37
            },
            {
                "char_id": 1306,
                "phantom_score": 55.45
            }
        ]
    },
    "100656979": {
        "rank": 2,
        "user_id": "3426521710",
        "username": "3426521710",
        "alias_name": "3426521710",
        "kuro_name": "3426521710",
        "waves_id": "100656979",
        "total_score": 568.47,
        "char_score_details": [
            {
                "char_id": 1405,
                "phantom_score": 44.06
            },
            {
                "char_id": 1301,
                "phantom_score": 195.59
            },
            {
                "char_id": 1102,
                "phantom_score": 4.72
            },
            {
                "char_id": 1605,
                "phantom_score": 67.47
            },
            {
                "char_id": 1205,
                "phantom_score": 196.35
            },
            {
                "char_id": 1305,
                "phantom_score": 176.53
            },
            {
                "char_id": 1505,
                "phantom_score": 111.49
            },
            {
                "char_id": 1203,
                "phantom_score": 141.47
            },
            {
                "char_id": 1404,
                "phantom_score": 1.76
            },
            {
                "char_id": 1503,
                "phantom_score": 19.47
            },
            {
                "char_id": 1608,
                "phantom_score": 102.62
            },
            {
                "char_id": 1411,
                "phantom_score": 114.94
            }
        ]
    },
    "120807850": {
        "rank": 3,
        "user_id": "1143695029",
        "username": "1143695029",
        "alias_name": "1143695029",
        "kuro_name": "1143695029",
        "waves_id": "120807850",
        "total_score": 559.4000000000001,
        "char_score_details": [
            {
                "char_id": 1503,
                "phantom_score": 108.91
            },
            {
                "char_id": 1203,
                "phantom_score": 170.64
            },
            {
                "char_id": 1604,
                "phantom_score": 165.68
            },
            {
                "char_id": 1102,
                "phantom_score": 152.81
            },
            {
                "char_id": 1305,
                "phantom_score": 149.58
            },
            {
                "char_id": 1505,
                "phantom_score": 106.2
            },
            {
                "char_id": 1603,
                "phantom_score": 191.09
            },
            {
                "char_id": 1107,
                "phantom_score": 168.19
            },
            {
                "char_id": 1105,
                "phantom_score": 144.81
            },
            {
                "char_id": 1607,
                "phantom_score": 150.18
            },
            {
                "char_id": 1507,
                "phantom_score": 175.49
            },
            {
                "char_id": 1506,
                "phantom_score": 163.57
            },
            {
                "char_id": 1608,
                "phantom_score": 192.82
            }
        ]
    },
    "122971985": {
        "rank": 1,
        "user_id": "3011546551",
        "username": "3011546551",
        "alias_name": "3011546551",
        "kuro_name": "3011546551",
        "waves_id": "122971985",
        "total_score": 924.81,
        "char_score_details": [
            {
                "char_id": 1102,
                "phantom_score": 69.1
            },
            {
                "char_id": 1602,
                "phantom_score": 4.8
            },
            {
                "char_id": 1303,
                "phantom_score": 37.1
            },
            {
                "char_id": 1301,
                "phantom_score": 190.09
            },
            {
                "char_id": 1405,
                "phantom_score": 176.22
            },
            {
                "char_id": 1504,
                "phantom_score": 185.71
            },
            {
                "char_id": 1305,
                "phantom_score": 181.06
            },
            {
                "char_id": 1605,
                "phantom_score": 172.38
            },
            {
                "char_id": 1306,
                "phantom_score": 191.73
            },
            {
                "char_id": 1203,
                "phantom_score": 4.65
            },
            {
                "char_id": 1505,
                "phantom_score": 85.24
            },
            {
                "char_id": 1410,
                "phantom_score": 133.19
            }
        ]
    },
    "101548515": {
        "rank": 5,
        "user_id": "710534694",
        "username": "710534694",
        "alias_name": "710534694",
        "kuro_name": "710534694",
        "waves_id": "101548515",
        "total_score": 179.83,
        "char_score_details": [
            {
                "char_id": 1502,
                "phantom_score": 170.05
            },
            {
                "char_id": 1202,
                "phantom_score": 143.29
            },
            {
                "char_id": 1301,
                "phantom_score": 168.59
            },
            {
                "char_id": 1102,
                "phantom_score": 160.23
            },
            {
                "char_id": 1503,
                "phantom_score": 179.83
            },
            {
                "char_id": 1404,
                "phantom_score": 148.86
            },
            {
                "char_id": 1602,
                "phantom_score": 164.19
            },
            {
                "char_id": 1601,
                "phantom_score": 29.24
            },
            {
                "char_id": 1303,
                "phantom_score": 114.57
            },
            {
                "char_id": 1304,
                "phantom_score": 174.36
            },
            {
                "char_id": 1305,
                "phantom_score": 147.34
            },
            {
                "char_id": 1505,
                "phantom_score": 163.79
            },
            {
                "char_id": 1106,
                "phantom_score": 29.58
            },
            {
                "char_id": 1603,
                "phantom_score": 153.51
            },
            {
                "char_id": 1203,
                "phantom_score": 150.53
            },
            {
                "char_id": 1506,
                "phantom_score": 137.49
            },
            {
                "char_id": 1507,
                "phantom_score": 169.55
            },
            {
                "char_id": 1608,
                "phantom_score": 156.59
            },
            {
                "char_id": 1104,
                "phantom_score": 6.42
            },
            {
                "char_id": 1410,
                "phantom_score": 153.09
            }
        ]
    }
}